VHDL/ha.vhdl
library ieee;
use ieee.std_logic_1164.all;

entity ha is	-- half adder
	port (		-- s: sum; c: carry
		a : in std_logic;	-- input: 1
		b : in std_logic;	-- input: 2
		s : out std_logic;	-- output: sum
		c : out std_logic	-- output: carry
	);
end ha;

architecture behavior of ha is
begin
	s <= a xor b;	-- sum
	c <= a and b;	-- carry
end behavior;

VHDL/fa.vhdl
library ieee;
use ieee.std_logic_1164.all;

entity fa is -- full adder
	port ( -- s: sum; c: carry
		a : in std_logic;
		b : in std_logic;
		c_in : in std_logic;
		s : out std_logic;
		c_out : out std_logic
	);
end fa;

architecture behavior of fa is
	component ha
		port ( -- s: sum; c: carry
			a : in std_logic;
			b : in std_logic;
			s : out std_logic;
			c : out std_logic
		);
	end component ha;
	
	signal s1, c1, c2 : std_logic;
begin
	halbaddierer1: ha port map(a, b, s1, c1);
	halbaddierer2: ha port map(c_in, s1, s, c2);
	
	c_out <= c1 or c2;
end behavior;

VHDL/fa_tb.vhdl
library ieee;
use ieee.std_logic_1164.all;

entity fa_tb is -- full adder testbench
end fa_tb;

architecture test of fa_tb is
	component fa is -- full adder
		port ( -- s: sum; c: carry
			a : in std_logic;
			b : in std_logic;
			c_in : std_logic;
			s : out std_logic;
			c_out : out std_logic
		);
	end component fa;
	
	signal a, b, c_in, s, c_out : std_logic := '0';
	
begin
	full_adder: fa port map(a, b, c_in, s, c_out);
	
	process begin
		a <= '0';
		b <= '0';
		c_in <= '0';
		wait for 1 ns; -- s = 0; c_out = 0
		a <= '0';
		b <= '0';
		c_in <= '1';
		wait for 1 ns; -- s = 1; c_out = 0
		a <= '0';
		b <= '1';
		c_in <= '0';
		wait for 1 ns; -- s = 1; c_out = 0
		a <= '0';
		b <= '1';
		c_in <= '1';
		wait for 1 ns; -- s = 0; c_out = 1
		a <= '1';
		b <= '0';
		c_in <= '0';
		wait for 1 ns; -- s = 1; c_out = 0
		a <= '1';
		b <= '0';
		c_in <= '1';
		wait for 1 ns; -- s = 0; c_out = 1
		a <= '1';
		b <= '1';
		c_in <= '0';
		wait for 1 ns; -- s = 0; c_out = 1
		a <= '1';
		b <= '1';
		c_in <= '1';
		wait for 1 ns; -- s = 1; c_out = 1
		wait;
	end process;
end test;

VHDL/fa_tb.vcd
$date
  Wed Mar 23 17:45:45 2022
$end
$version
  GHDL v0
$end
$timescale
  1 fs
$end
$scope module standard $end
$upscope $end
$scope module std_logic_1164 $end
$upscope $end
$scope module fa_tb $end
$var reg 1 ! a $end
$var reg 1 " b $end
$var reg 1 # c_in $end
$var reg 1 $ s $end
$var reg 1 % c_out $end
$scope module full_adder $end
$var reg 1 & a $end
$var reg 1 ' b $end
$var reg 1 ( c_in $end
$var reg 1 ) s $end
$var reg 1 * c_out $end
$var reg 1 + s1 $end
$var reg 1 , c1 $end
$var reg 1 - c2 $end
$scope module half_adder_1 $end
$var reg 1 . a $end
$var reg 1 / b $end
$var reg 1 0 s $end
$var reg 1 1 c $end
$upscope $end
$scope module half_adder_2 $end
$var reg 1 2 a $end
$var reg 1 3 b $end
$var reg 1 4 s $end
$var reg 1 5 c $end
$upscope $end
$upscope $end
$upscope $end
$enddefinitions $end
#0
0!
0"
0#
0$
0%
0&
0'
0(
0)
0*
0+
0,
0-
0.
0/
00
01
02
03
04
05
#1000000
1#
1$
1(
1)
12
14
#2000000
1"
0#
1$
1'
0(
1)
1+
1/
10
02
13
14
#3000000
1#
0$
1%
1(
0)
1*
1-
12
04
15
#4000000
1!
0"
0#
1$
0%
1&
0'
0(
1)
0*
0-
1.
0/
02
14
05
#5000000
1#
0$
1%
1(
0)
1*
1-
12
04
15
#6000000
1"
0#
0$
1'
0(
0)
0+
1,
0-
1/
00
11
02
03
04
05
#7000000
1#
1$
1(
1)
12
14
