VHDL/fifo_wptr_full.vhdl
library IEEE;
use IEEE.std_logic_1164.all;
use IEEE.numeric_std.all;

entity fifo_wptr_full is generic(addressSize:integer:=8);
    port(
        wfull: out std_logic;
        waddr: out std_logic_vector(addressSize-1 downto 0);
        wptr: out std_logic_vector(addressSize downto 0);
        wq2_rptr: in std_logic_vector(addressSize downto 0);
        winc: in std_logic;
        wclk: in std_logic;
        wrst_n: in std_logic
    );
end entity fifo_wptr_full;

architecture fifo_wptr_full_behaviour of fifo_wptr_full is
    signal wbin: std_logic_vector(addressSize downto 0);
    signal wgraynext: std_logic_vector(addressSize downto 0);
    signal wbinnext: std_logic_vector(addressSize downto 0);
    signal wfull_val: std_logic;
    signal wfull_tmp: std_logic;

    function To_Std_Logic(L: BOOLEAN) return std_ulogic is
    begin
        if L then
          return('1');
       else
          return('0');
       end if;
    end function To_Std_Logic; 

    function Std_Logic_To_Std_Logic_Vector(b: std_logic) return std_logic_vector is
    variable ret: std_logic_vector(addressSize downto 0);
    begin
        ret := (others => '0');
        ret(0) := b;
        return ret;
    end function Std_Logic_To_Std_Logic_Vector; 

    begin
        waddr <= wbin(addressSize-1 downto 0);
        wbinnext <= std_logic_vector(unsigned(wbin)+unsigned(Std_Logic_To_Std_Logic_Vector(winc and (not wfull_tmp))) );
        wgraynext <= std_logic_vector(shift_right(unsigned(wbinnext),1)) xor wbinnext;
        wfull_val <= (wgraynext(addressSize) xor wq2_rptr(addressSize)) and
                     (wgraynext(addressSize-1) xor wq2_rptr(addressSize-1)) and
                     To_Std_Logic(wgraynext(addressSize-2 downto 0) = wq2_rptr(addressSize-2 downto 0));

        process(wclk,wrst_n)
        begin
            if rising_edge(wclk) or falling_edge(wrst_n) then
                if (wrst_n='0') then
                    --Pointer
                    wbin <= (others => '0');
                    wptr <= (others => '0');
                    --FIFO full
                    wfull <= '0';
                    wfull_tmp <= '0';
                else
                    --Pointer
                    wbin <= wbinnext;
                    wptr <= wgraynext;
                    --FIFO full
                    wfull <= wfull_val;
                    wfull_tmp <= wfull_val;
                end if;
            end if;
        end process;

    end architecture fifo_wptr_full_behaviour;

VHDL/fifo_rptr_empty.vhdl
library IEEE;
use IEEE.std_logic_1164.all;
use IEEE.numeric_std.all;

entity fifo_rptr_empty is generic(addressSize:integer:=8);
    port(
        rempty: out std_logic;                                  --Active HIGH when readpointer is equal to writepointer (see paper)
        raddr: out std_logic_vector(addressSize-1 downto 0);
        rptr: out std_logic_vector(addressSize downto 0);
        rq2_wptr: in std_logic_vector(addressSize downto 0);
        rinc: in std_logic;
        rclk: in std_logic;
        rrst_n: in std_logic
    );
end entity fifo_rptr_empty;

architecture fifo_rptr_empty_behaviour of fifo_rptr_empty is
    signal rbin: std_logic_vector(addressSize downto 0);
    signal rgraynext: std_logic_vector(addressSize downto 0);
    signal rbinnext: std_logic_vector(addressSize downto 0);
    signal rempty_val: std_logic;
    signal rempty_tmp: std_logic;

    function To_Std_Logic(L: BOOLEAN) return std_ulogic is
    begin
        if L then
          return('1');
       else
          return('0');
       end if;
    end function To_Std_Logic; 

    function Std_Logic_To_Std_Logic_Vector(b: std_logic) return std_logic_vector is
    variable ret: std_logic_vector(addressSize downto 0);
    begin
        ret := (others => '0');
        ret(0) := b;
        return ret;
    end function Std_Logic_To_Std_Logic_Vector; 

    begin
        raddr <= rbin(addressSize-1 downto 0);
        rbinnext <= std_logic_vector(unsigned(rbin)+unsigned(Std_Logic_To_Std_Logic_Vector(rinc and (not rempty_tmp))) );
        rgraynext <= std_logic_vector(shift_right(unsigned(rbinnext),1)) xor rbinnext;
        rempty_val <= To_Std_logic(rgraynext = rq2_wptr);

        process(rclk,rrst_n)
        begin
            if rising_edge(rclk) or falling_edge(rrst_n) then
                if (rrst_n='0') then
                    --Pointer
                    rbin <= (others => '0');
                    rptr <= (others => '0');
                    --FIFO empty
                    rempty <= '1';
                    rempty_tmp <= '1';
                else
                    --Pointer
                    rbin <= rbinnext;
                    rptr <= rgraynext;
                    --FIFO empty
                    rempty <= rempty_val;
                    rempty_tmp <= rempty_val;
                end if;
            end if;
        end process;

    end architecture fifo_rptr_empty_behaviour;

VHDL/fifo_mem.vhdl
library IEEE;
use IEEE.std_logic_1164.all;
use IEEE.numeric_std.all;


entity fifo_mem is generic(dataSize:integer:=8;addressSize:integer:=8);
    port(
        rdata: out std_logic_vector(dataSize-1 downto 0);
        wdata: in std_logic_vector(dataSize-1 downto 0);
        raddr: in std_logic_vector(addressSize-1 downto 0);
        waddr: in std_logic_vector(addressSize-1 downto 0);
        wclken: in std_logic;
        wfull: in std_logic;
        wclk: in std_logic
    );
end entity fifo_mem;
architecture fifo_mem_behaviour of fifo_mem is
    subtype WORD is std_logic_vector(dataSize-1 downto 0);
    type MEMORY is array(0 to 2**addressSize-1) of WORD;
    signal ram:MEMORY;
    
    begin
        process(wclk,wdata,raddr)
        variable ram_waddr:natural range 0 to 2**addressSize-1;
        variable ram_raddr:natural range 0 to 2**addressSize-1;
        begin
            ram_waddr := to_integer(UNSIGNED(waddr));
            ram_raddr := to_integer(UNSIGNED(raddr));
            rdata <= ram(ram_raddr);

            if rising_edge(wclk) then
                if (wclken='1' and wfull='0') then
                    ram(ram_waddr) <= wdata;
                end if;

            end if;
        end process;
    end architecture fifo_mem_behaviour;

VHDL/fifo_sync_w2r.vhdl
library IEEE;
use IEEE.std_logic_1164.all;
use IEEE.numeric_std.all;

entity fifo_sync_w2r is generic(addressSize:integer:=8);
    port(
        rq2_wptr: out std_logic_vector(addressSize downto 0);
        wptr: in std_logic_vector(addressSize downto 0);
        rrst_n: in std_logic;
        rclk: in std_logic
    );
end entity fifo_sync_w2r;

architecture fifo_sync_w2r_behaviour of fifo_sync_w2r is
    signal rq1_wptr: std_logic_vector(addressSize downto 0);
    
    begin
        process(rclk,rrst_n)
        begin
            if rising_edge(rclk) or falling_edge(rrst_n) then
                if (rrst_n='0') then
                    rq2_wptr <= (others => '0');
                    rq1_wptr <= (others => '0');
                else
                    rq2_wptr <= rq1_wptr;
                    rq1_wptr <= wptr;
                end if;
            end if;
        end process;
    end architecture fifo_sync_w2r_behaviour;

VHDL/fifo_sync_r2w.vhdl
library IEEE;
use IEEE.std_logic_1164.all;
use IEEE.numeric_std.all;

entity fifo_sync_r2w is generic(addressSize:integer:=8);
    port(
        wq2_rptr: out std_logic_vector(addressSize downto 0);
        rptr: in std_logic_vector(addressSize downto 0);
        wrst_n: in std_logic;
        wclk: in std_logic
    );
end entity fifo_sync_r2w;

architecture fifo_sync_r2w_behaviour of fifo_sync_r2w is
    signal wq1_rptr: std_logic_vector(addressSize downto 0);
    
    begin
        process(wclk,wrst_n)
        begin
            if rising_edge(wclk) or falling_edge(wrst_n) then
                if (wrst_n='0') then
                    wq2_rptr <= (others => '0');
                    wq1_rptr <= (others => '0');
                else
                    wq2_rptr <= wq1_rptr;
                    wq1_rptr <= rptr;
                end if;
            end if;
        end process;
    end architecture fifo_sync_r2w_behaviour;

VHDL/fifo.vhdl
library IEEE;
use IEEE.std_logic_1164.all;
use IEEE.numeric_std.all;


entity fifo is generic(dataSize:integer:=8;addressSize:integer:=8);
    port(
        rdata: out std_logic_vector(dataSize-1 downto 0);
        wfull: out std_logic;
        rempty: out std_logic;
        wdata: in std_logic_vector(dataSize-1 downto 0);
        winc, wclk, wrst_n: in std_logic;
        rinc, rclk, rrst_n: in std_logic
    );
end entity fifo;
architecture fifo_behaviour of fifo is
    component fifo_sync_r2w 
    generic(addressSize:integer:=8);
    port(
        wq2_rptr: out std_logic_vector(addressSize downto 0);
        rptr: in std_logic_vector(addressSize downto 0);
        wrst_n: in std_logic;
        wclk: in std_logic        
    );
    end component fifo_sync_r2w;

    component fifo_sync_w2r
    generic(addressSize:integer:=8);
    port(
        rq2_wptr: out std_logic_vector(addressSize downto 0);
        wptr: in std_logic_vector(addressSize downto 0);
        rrst_n: in std_logic;
        rclk: in std_logic   
    );
    end component fifo_sync_w2r;

    component fifo_mem 
    generic(dataSize:integer:=8;addressSize:integer:=8);
    port(
        rdata: out std_logic_vector(dataSize-1 downto 0);
        wdata: in std_logic_vector(dataSize-1 downto 0);
        raddr: in std_logic_vector(addressSize-1 downto 0);
        waddr: in std_logic_vector(addressSize-1 downto 0);
        wclken: in std_logic;
        wfull: in std_logic;
        wclk: in std_logic
    );
    end component fifo_mem;

    component fifo_rptr_empty 
    generic(addressSize:integer:=8);
    port(
        rempty: out std_logic;
        raddr: out std_logic_vector(addressSize-1 downto 0);
        rptr: out std_logic_vector(addressSize downto 0);
        rq2_wptr: in std_logic_vector(addressSize downto 0);
        rinc: in std_logic;
        rclk: in std_logic;
        rrst_n: in std_logic
    );
    end component fifo_rptr_empty;

    component fifo_wptr_full 
    generic(addressSize:integer:=8);
    port(
        wfull: out std_logic;
        waddr: out std_logic_vector(addressSize-1 downto 0);
        wptr: out std_logic_vector(addressSize downto 0);
        wq2_rptr: in std_logic_vector(addressSize downto 0);
        winc: in std_logic;
        wclk: in std_logic;
        wrst_n: in std_logic
    );
    end component fifo_wptr_full;

    signal waddr, raddr: std_logic_vector(addressSize-1 downto 0);
    signal wptr, rptr, wq2_rptr, rq2_wptr: std_logic_vector(addressSize downto 0);
    signal wfull_var: std_logic;
begin
    wfull <= wfull_var;
    sync_r2w: fifo_sync_r2w generic map(addressSize => addressSize) port map(wq2_rptr, rptr, wrst_n, wclk);
    sync_w2r: fifo_sync_w2r generic map(addressSize => addressSize) port map(rq2_wptr, wptr, rrst_n, rclk);
    mem: fifo_mem generic map(dataSize =>dataSize, addressSize => addressSize) port map(rdata, wdata, raddr, waddr, winc, wfull_var, wclk);
    rptr_empty: fifo_rptr_empty generic map(addressSize => addressSize) port map(rempty, raddr, rptr, rq2_wptr, rinc, rclk, rrst_n);
    wptr_full: fifo_wptr_full generic map(addressSize => addressSize) port map(wfull_var, waddr, wptr, wq2_rptr, winc, wclk, wrst_n);
    
end architecture fifo_behaviour;

VHDL/fifo_tb.vhdl
library ieee;
use ieee.std_logic_1164.all;

entity fifo_tb is -- first-in first-out testbench (parallel-in parallel-out)
end fifo_tb;

architecture test of fifo_tb is
	component fifo is -- first-in first-out (parallel-in parallel-out)
		generic(dataSize:integer:=8;addressSize:integer:=8);
        port(
            rdata: out std_logic_vector(dataSize-1 downto 0);
            wfull: out std_logic;
            rempty: out std_logic;
            wdata: in std_logic_vector(dataSize-1 downto 0);
            winc, wclk, wrst_n: in std_logic;
            rinc, rclk, rrst_n: in std_logic
    );
	end component fifo;
	
	signal rdata: std_logic_vector(7 downto 0);
    signal wfull: std_logic;
    signal rempty: std_logic;
    signal wdata: std_logic_vector(7 downto 0);
    signal winc, wclk, wrst_n: std_logic;
    signal rinc, rclk, rrst_n: std_logic;
begin
    
	fi_fo: fifo generic map(dataSize => 8, addressSize => 2) port map(rdata, wfull, rempty, wdata, winc, wclk, wrst_n,rinc, rclk, rrst_n);
	process begin
        rinc <= '0';
        winc <= '0';
        rclk <= '0';
        wclk <= '0';
        wdata <= "00000000";
        
        --reset synchronisation
        wrst_n <= '1';
        rrst_n <= '1';
        wait for 1 ns;
        wrst_n <= '0'; 
        rrst_n <= '0';
        wait for 1 ns;
        wrst_n <= '1';
        rrst_n <= '1';

        -- One cycle for clean startup
        wait for 1 ns;wclk <= '1';rclk <= '1';wait for 1 ns; wclk <= '0';rclk <= '0';

		-- fill fifo with some values
        winc <= '1';
        wait for 1 ns;wclk <= '1';rclk <= '1';wait for 1 ns; wclk <= '0';rclk <= '0';
        
        wdata <= "00000001";
        wait for 1 ns;wclk <= '1';rclk <= '1';wait for 1 ns; wclk <= '0';rclk <= '0';

        wdata <= "00000010";
        wait for 1 ns;wclk <= '1';rclk <= '1';wait for 1 ns; wclk <= '0';rclk <= '0';

        wdata <= "00000011";
        wait for 1 ns;wclk <= '1';rclk <= '1';wait for 1 ns; wclk <= '0';rclk <= '0';
       

        -- read out for several cycles
        winc <= '0';
        rinc <= '1';
        wait for 1 ns;wclk <= '1';rclk <= '1';wait for 1 ns; wclk <= '0';rclk <= '0';
        wait for 1 ns;wclk <= '1';rclk <= '1';wait for 1 ns; wclk <= '0';rclk <= '0';
        wait for 1 ns;wclk <= '1';rclk <= '1';wait for 1 ns; wclk <= '0';rclk <= '0';
        wait for 1 ns;wclk <= '1';rclk <= '1';wait for 1 ns; wclk <= '0';rclk <= '0';
        wait for 1 ns;wclk <= '1';rclk <= '1';wait for 1 ns; wclk <= '0';rclk <= '0';
        wait for 1 ns;wclk <= '1';rclk <= '1';wait for 1 ns; wclk <= '0';rclk <= '0';
        wait for 1 ns;wclk <= '1';rclk <= '1';wait for 1 ns; wclk <= '0';rclk <= '0';
        
        
		wait;
	end process;
end test;

VHDL/fifo_tb.vcd
$date
  Wed Mar 23 17:40:18 2022
$end
$version
  GHDL v0
$end
$timescale
  1 fs
$end
$scope module standard $end
$upscope $end
$scope module std_logic_1164 $end
$upscope $end
$scope module numeric_std $end
$upscope $end
$scope module fifo_tb $end
$var reg 8 ! rdata[7:0] $end
$var reg 1 " wfull $end
$var reg 1 # rempty $end
$var reg 8 $ wdata[7:0] $end
$var reg 1 % winc $end
$var reg 1 & wclk $end
$var reg 1 ' wrst_n $end
$var reg 1 ( rinc $end
$var reg 1 ) rclk $end
$var reg 1 * rrst_n $end
$scope module fi_fo $end
$var reg 8 + rdata[7:0] $end
$var reg 1 , wfull $end
$var reg 1 - rempty $end
$var reg 8 . wdata[7:0] $end
$var reg 1 / winc $end
$var reg 1 0 wclk $end
$var reg 1 1 wrst_n $end
$var reg 1 2 rinc $end
$var reg 1 3 rclk $end
$var reg 1 4 rrst_n $end
$var reg 2 5 waddr[1:0] $end
$var reg 2 6 raddr[1:0] $end
$var reg 3 7 wptr[2:0] $end
$var reg 3 8 rptr[2:0] $end
$var reg 3 9 wq2_rptr[2:0] $end
$var reg 3 : rq2_wptr[2:0] $end
$var reg 1 ; wfull_var $end
$scope module sync_r2w $end
$var reg 3 < wq2_rptr[2:0] $end
$var reg 3 = rptr[2:0] $end
$var reg 1 > wrst_n $end
$var reg 1 ? wclk $end
$var reg 3 @ wq1_rptr[2:0] $end
$upscope $end
$scope module sync_w2r $end
$var reg 3 A rq2_wptr[2:0] $end
$var reg 3 B wptr[2:0] $end
$var reg 1 C rrst_n $end
$var reg 1 D rclk $end
$var reg 3 E rq1_wptr[2:0] $end
$upscope $end
$scope module mem $end
$var reg 8 F rdata[7:0] $end
$var reg 8 G wdata[7:0] $end
$var reg 2 H raddr[1:0] $end
$var reg 2 I waddr[1:0] $end
$var reg 1 J wclken $end
$var reg 1 K wfull $end
$var reg 1 L wclk $end
$comment ram is not handled $end
$upscope $end
$scope module rptr_empty $end
$var reg 1 M rempty $end
$var reg 2 N raddr[1:0] $end
$var reg 3 O rptr[2:0] $end
$var reg 3 P rq2_wptr[2:0] $end
$var reg 1 Q rinc $end
$var reg 1 R rclk $end
$var reg 1 S rrst_n $end
$var reg 3 T rbin[2:0] $end
$var reg 3 U rgraynext[2:0] $end
$var reg 3 V rbinnext[2:0] $end
$var reg 1 W rempty_val $end
$var reg 1 X rempty_tmp $end
$upscope $end
$scope module wptr_full $end
$var reg 1 Y wfull $end
$var reg 2 Z waddr[1:0] $end
$var reg 3 [ wptr[2:0] $end
$var reg 3 \ wq2_rptr[2:0] $end
$var reg 1 ] winc $end
$var reg 1 ^ wclk $end
$var reg 1 _ wrst_n $end
$var reg 3 ` wbin[2:0] $end
$var reg 3 a wgraynext[2:0] $end
$var reg 3 b wbinnext[2:0] $end
$var reg 1 c wfull_val $end
$var reg 1 d wfull_tmp $end
$upscope $end
$upscope $end
$upscope $end
$enddefinitions $end
#0
bUUUUUUUU !
U"
U#
b00000000 $
0%
0&
1'
0(
0)
1*
bUUUUUUUU +
U,
U-
b00000000 .
0/
00
11
02
03
14
bUU 5
bUU 6
bUUU 7
bUUU 8
bUUU 9
bUUU :
U;
bUUU <
bUUU =
1>
0?
bUUU @
bUUU A
bUUU B
1C
0D
bUUU E
bUUUUUUUU F
b00000000 G
bUU H
bUU I
0J
UK
0L
UM
bUU N
bUUU O
bUUU P
0Q
0R
1S
bUUU T
bXXX U
bXXX V
0W
UX
UY
bUU Z
bUUU [
bUUU \
0]
0^
1_
bUUU `
bXXX a
bXXX b
0c
Ud
#1000000
0"
1#
0'
0*
0,
1-
01
04
b00 5
b00 6
b000 7
b000 8
b000 9
b000 :
0;
b000 <
b000 =
0>
b000 @
b000 A
b000 B
0C
b000 E
b00 H
b00 I
0K
1M
b00 N
b000 O
b000 P
0S
b000 T
b000 U
b000 V
1W
1X
0Y
b00 Z
b000 [
b000 \
0_
b000 `
b000 a
b000 b
0d
#2000000
1'
1*
11
14
1>
1C
1S
1_
#3000000
1&
1)
10
13
1?
1D
1L
1R
1^
#4000000
1%
0&
0)
1/
00
03
0?
0D
1J
0L
0R
1]
0^
b001 a
b001 b
#5000000
1&
1)
10
13
b01 5
b001 7
1?
b001 B
1D
b01 I
1L
1R
b01 Z
b001 [
1^
b001 `
b011 a
b010 b
#6000000
b00000000 !
b00000001 $
0&
0)
b00000000 +
b00000001 .
00
03
0?
0D
b00000000 F
b00000001 G
0L
0R
0^
#7000000
1&
1)
10
13
b10 5
b011 7
1?
b011 B
1D
b001 E
b10 I
1L
1R
b10 Z
b011 [
1^
b010 `
b010 a
b011 b
#8000000
b00000010 $
0&
0)
b00000010 .
00
03
0?
0D
b00000010 G
0L
0R
0^
#9000000
1&
1)
10
13
b11 5
b010 7
b001 :
1?
b001 A
b010 B
1D
b011 E
b11 I
1L
b001 P
1R
0W
b11 Z
b010 [
1^
b011 `
b110 a
b100 b
1c
#10000000
b00000011 $
0&
0)
b00000011 .
00
03
0?
0D
b00000011 G
0L
0R
0^
#11000000
1"
0#
1&
1)
1,
0-
10
13
b00 5
b110 7
b011 :
1;
1?
b011 A
b110 B
1D
b010 E
b00 I
1K
1L
0M
b011 P
1R
0X
1Y
b00 Z
b110 [
1^
b100 `
1d
#12000000
0%
0&
1(
0)
0/
00
12
03
0?
0D
0J
0L
1Q
0R
b001 U
b001 V
0]
0^
#13000000
b00000001 !
1&
1)
b00000001 +
10
13
b01 6
b001 8
b010 :
b001 =
1?
b010 A
1D
b110 E
b00000001 F
b01 H
1L
b01 N
b001 O
b010 P
1R
b001 T
b011 U
b010 V
1^
#14000000
0&
0)
00
03
0?
0D
0L
0R
0^
#15000000
b00000010 !
1&
1)
b00000010 +
10
13
b10 6
b011 8
b110 :
b011 =
1?
b001 @
b110 A
1D
b00000010 F
b10 H
1L
b10 N
b011 O
b110 P
1R
b010 T
b010 U
b011 V
1^
#16000000
0&
0)
00
03
0?
0D
0L
0R
0^
#17000000
b00000011 !
1&
1)
b00000011 +
10
13
b11 6
b010 8
b001 9
b001 <
b010 =
1?
b011 @
1D
b00000011 F
b11 H
1L
b11 N
b010 O
1R
b011 T
b110 U
b100 V
1W
b001 \
1^
0c
#18000000
0&
0)
00
03
0?
0D
0L
0R
0^
#19000000
b00000000 !
0"
1#
1&
1)
b00000000 +
0,
1-
10
13
b00 6
b110 8
b011 9
0;
b011 <
b110 =
1?
b010 @
1D
b00000000 F
b00 H
0K
1L
1M
b00 N
b110 O
1R
b100 T
1X
0Y
b011 \
1^
0d
#20000000
0&
0)
00
03
0?
0D
0L
0R
0^
#21000000
1&
1)
10
13
b010 9
b010 <
1?
b110 @
1D
1L
1R
b010 \
1^
#22000000
0&
0)
00
03
0?
0D
0L
0R
0^
#23000000
1&
1)
10
13
b110 9
b110 <
1?
1D
1L
1R
b110 \
1^
#24000000
0&
0)
00
03
0?
0D
0L
0R
0^
#25000000
1&
1)
10
13
1?
1D
1L
1R
1^
#26000000
1%
0&
0(
0)
1/
00
02
03
0?
0D
1J
0L
0Q
0R
1]
0^
b111 a
b101 b
#27000000
1&
1)
10
13
b01 5
b111 7
1?
b111 B
1D
b01 I
1L
1R
b01 Z
b111 [
1^
b101 `
b101 a
b110 b
#28000000
b00000011 !
b11111111 $
0&
0)
b00000011 +
b11111111 .
00
03
0?
0D
b00000011 F
b11111111 G
0L
0R
0^
#29000000
1&
1)
10
13
b10 5
b101 7
1?
b101 B
1D
b111 E
b10 I
1L
1R
b10 Z
b101 [
1^
b110 `
b100 a
b111 b
#30000000
b11111110 $
0&
0)
b11111110 .
00
03
0?
0D
b11111110 G
0L
0R
0^
#31000000
1&
1)
10
13
b11 5
b100 7
b111 :
1?
b111 A
b100 B
1D
b101 E
b11 I
1L
b111 P
1R
0W
b11 Z
b100 [
1^
b111 `
b000 a
b000 b
1c
#32000000
b11111111 $
0&
0)
b11111111 .
00
03
0?
0D
b11111111 G
0L
0R
0^
#33000000
1"
0#
1&
1)
1,
0-
10
13
b00 5
b000 7
b101 :
1;
1?
b101 A
b000 B
1D
b100 E
b00 I
1K
1L
0M
b101 P
1R
0X
1Y
b00 Z
b000 [
1^
b000 `
1d
#34000000
0%
0&
1(
0)
0/
00
12
03
0?
0D
0J
0L
1Q
0R
b111 U
b101 V
0]
0^
#35000000
b11111111 !
1&
1)
b11111111 +
10
13
b01 6
b111 8
b100 :
b111 =
1?
b100 A
1D
b000 E
b11111111 F
b01 H
1L
b01 N
b111 O
b100 P
1R
b101 T
b101 U
b110 V
1^
#36000000
0&
0)
00
03
0?
0D
0L
0R
0^
#37000000
b11111110 !
1&
1)
b11111110 +
10
13
b10 6
b101 8
b000 :
b101 =
1?
b111 @
b000 A
1D
b11111110 F
b10 H
1L
b10 N
b101 O
b000 P
1R
b110 T
b100 U
b111 V
1^
#38000000
0&
0)
00
03
0?
0D
0L
0R
0^
#39000000
b11111111 !
1&
1)
b11111111 +
10
13
b11 6
b100 8
b111 9
b111 <
b100 =
1?
b101 @
1D
b11111111 F
b11 H
1L
b11 N
b100 O
1R
b111 T
b000 U
b000 V
1W
b111 \
1^
0c
#40000000
0&
0)
00
03
0?
0D
0L
0R
0^
#41000000
b00000011 !
0"
1#
1&
1)
b00000011 +
0,
1-
10
13
b00 6
b000 8
b101 9
0;
b101 <
b000 =
1?
b100 @
1D
b00000011 F
b00 H
0K
1L
1M
b00 N
b000 O
1R
b000 T
1X
0Y
b101 \
1^
0d
#42000000
0&
0)
00
03
0?
0D
0L
0R
0^
#43000000
1&
1)
10
13
b100 9
b100 <
1?
b000 @
1D
1L
1R
b100 \
1^
#44000000
0&
0)
00
03
0?
0D
0L
0R
0^
#45000000
1&
1)
10
13
b000 9
b000 <
1?
1D
1L
1R
b000 \
1^
