VHDL/pipo.vhdl
library ieee;
use ieee.std_logic_1164.all;

entity pipo is -- parallel-in parallel-out (8-Bit Register)
	port ( -- c: clock; r: reset
		a : in std_logic_vector(7 downto 0);
		c : in std_logic;
		r : in std_logic;
		b : out std_logic_vector(7 downto 0)
	);
end pipo;

architecture behavior of pipo is
	-- m: memory
	signal m : std_logic_vector(7 downto 0);
begin
    
	process(c, r) begin
    if r = '1' then m <= (others => '0');
    elsif rising_edge(c) then
      m <= a;
    end if;
  	b <= m;
  end process;
  
end behavior;

VHDL/pipo_tb.vhdl
library ieee;
use ieee.std_logic_1164.all;
use ieee.numeric_std.all;

entity pipo_tb is
end pipo_tb;

architecture testbench of pipo_tb is

component pipo is -- parallel-in parallel-out (8-Bit Register)
	port ( -- c: clock; r: reset
		a : in std_logic_vector(7 downto 0);
		c : in std_logic;
		r : in std_logic;
		b : out std_logic_vector(7 downto 0)
	);
end component;

signal c, r : std_logic;
signal a, b: std_logic_vector(7 downto 0);

begin
    reg: pipo port map(c => c, r => r, a => a, b => b);
    process begin
        forloopc: for i in 50 downto 0 loop
            c <= '0';
            wait for 5 ns;
            c <= '1';
            wait for 5 ns;
        end loop;
        wait;

    end process;
    
    process begin
        a <= "00010001";
        wait for 20 ns;
        a <= "00100001";
        wait for 20 ns;
        a <= "01000001";
        wait for 20 ns;
        r <= '1';
        wait for 10 ns;
        a <= "10000001";
        wait for 20 ns;
        r <= '0';
        wait for 10 ns;
        wait;
    end process;
   
    

end testbench;

VHDL/pipo_tb.vcd
$date
  Mon Jan 17 12:51:15 2022
$end
$version
  GHDL v0
$end
$timescale
  1 fs
$end
$scope module standard $end
$upscope $end
$scope module std_logic_1164 $end
$upscope $end
$scope module numeric_std $end
$upscope $end
$scope module pipo_tb $end
$var reg 1 ! c $end
$var reg 1 " r $end
$var reg 8 # a[7:0] $end
$var reg 8 $ b[7:0] $end
$scope module reg $end
$var reg 8 % a[7:0] $end
$var reg 1 & c $end
$var reg 1 ' r $end
$var reg 8 ( b[7:0] $end
$var reg 8 ) m[7:0] $end
$upscope $end
$upscope $end
$enddefinitions $end
#0
0!
U"
b00010001 #
bUUUUUUUU $
b00010001 %
0&
U'
bUUUUUUUU (
bUUUUUUUU )
#5000000
1!
1&
b00010001 )
#10000000
0!
b00010001 $
0&
b00010001 (
#15000000
1!
1&
#20000000
0!
b00100001 #
b00100001 %
0&
#25000000
1!
1&
b00100001 )
#30000000
0!
b00100001 $
0&
b00100001 (
#35000000
1!
1&
#40000000
0!
b01000001 #
b01000001 %
0&
#45000000
1!
1&
b01000001 )
#50000000
0!
b01000001 $
0&
b01000001 (
#55000000
1!
1&
#60000000
0!
1"
0&
1'
b00000000 )
#65000000
1!
b00000000 $
1&
b00000000 (
#70000000
0!
b10000001 #
b10000001 %
0&
#75000000
1!
1&
#80000000
0!
0&
#85000000
1!
1&
#90000000
0!
0"
0&
0'
#95000000
1!
1&
b10000001 )
#100000000
0!
b10000001 $
0&
b10000001 (
#105000000
1!
1&
#110000000
0!
0&
#115000000
1!
1&
#120000000
0!
0&
#125000000
1!
1&
#130000000
0!
0&
#135000000
1!
1&
#140000000
0!
0&
#145000000
1!
1&
#150000000
0!
0&
#155000000
1!
1&
#160000000
0!
0&
#165000000
1!
1&
#170000000
0!
0&
#175000000
1!
1&
#180000000
0!
0&
#185000000
1!
1&
#190000000
0!
0&
#195000000
1!
1&
#200000000
0!
0&
#205000000
1!
1&
#210000000
0!
0&
#215000000
1!
1&
#220000000
0!
0&
#225000000
1!
1&
#230000000
0!
0&
#235000000
1!
1&
#240000000
0!
0&
#245000000
1!
1&
#250000000
0!
0&
#255000000
1!
1&
#260000000
0!
0&
#265000000
1!
1&
#270000000
0!
0&
#275000000
1!
1&
#280000000
0!
0&
#285000000
1!
1&
#290000000
0!
0&
#295000000
1!
1&
#300000000
0!
0&
#305000000
1!
1&
#310000000
0!
0&
#315000000
1!
1&
#320000000
0!
0&
#325000000
1!
1&
#330000000
0!
0&
#335000000
1!
1&
#340000000
0!
0&
#345000000
1!
1&
#350000000
0!
0&
#355000000
1!
1&
#360000000
0!
0&
#365000000
1!
1&
#370000000
0!
0&
#375000000
1!
1&
#380000000
0!
0&
#385000000
1!
1&
#390000000
0!
0&
#395000000
1!
1&
#400000000
0!
0&
#405000000
1!
1&
#410000000
0!
0&
#415000000
1!
1&
#420000000
0!
0&
#425000000
1!
1&
#430000000
0!
0&
#435000000
1!
1&
#440000000
0!
0&
#445000000
1!
1&
#450000000
0!
0&
#455000000
1!
1&
#460000000
0!
0&
#465000000
1!
1&
#470000000
0!
0&
#475000000
1!
1&
#480000000
0!
0&
#485000000
1!
1&
#490000000
0!
0&
#495000000
1!
1&
#500000000
0!
0&
#505000000
1!
1&
