VHDL/fifo_wptr_full.vhdl
library IEEE;
use IEEE.std_logic_1164.all;
use IEEE.numeric_std.all;

entity fifo_wptr_full is generic(addressSize:integer:=8);
    port(
        wfull: out std_logic;
        waddr: out std_logic_vector(addressSize-1 downto 0);
        wptr: out std_logic_vector(addressSize downto 0);
        wq2_rptr: in std_logic_vector(addressSize downto 0);
        winc: in std_logic;
        wclk: in std_logic;
        wrst_n: in std_logic
    );
end entity fifo_wptr_full;

architecture fifo_wptr_full_behaviour of fifo_wptr_full is
    signal wbin: std_logic_vector(addressSize downto 0);
    signal wgraynext: std_logic_vector(addressSize downto 0);
    signal wbinnext: std_logic_vector(addressSize downto 0);
    signal wfull_val: std_logic;
    signal wfull_tmp: std_logic;

    function To_Std_Logic(L: BOOLEAN) return std_ulogic is
    begin
        if L then
          return('1');
       else
          return('0');
       end if;
    end function To_Std_Logic; 

    function Std_Logic_To_Std_Logic_Vector(b: std_logic) return std_logic_vector is
    variable ret: std_logic_vector(addressSize downto 0);
    begin
        ret := (others => '0');
        ret(0) := b;
        return ret;
    end function Std_Logic_To_Std_Logic_Vector; 

    begin
        waddr <= wbin(addressSize-1 downto 0);
        wbinnext <= std_logic_vector(unsigned(wbin)+unsigned(Std_Logic_To_Std_Logic_Vector(winc and (not wfull_tmp))) );
        wgraynext <= std_logic_vector(shift_right(unsigned(wbinnext),1)) xor wbinnext;
        wfull_val <= (wgraynext(addressSize) xor wq2_rptr(addressSize)) and
                     (wgraynext(addressSize-1) xor wq2_rptr(addressSize-1)) and
                     To_Std_Logic(wgraynext(addressSize-2 downto 0) = wq2_rptr(addressSize-2 downto 0));

        process(wclk,wrst_n)
        begin
            if rising_edge(wclk) or falling_edge(wrst_n) then
                if (wrst_n='0') then
                    --Pointer
                    wbin <= (others => '0');
                    wptr <= (others => '0');
                    --FIFO full
                    wfull <= '0';
                    wfull_tmp <= '0';
                else
                    --Pointer
                    wbin <= wbinnext;
                    wptr <= wgraynext;
                    --FIFO full
                    wfull <= wfull_val;
                    wfull_tmp <= wfull_val;
                end if;
            end if;
        end process;

    end architecture fifo_wptr_full_behaviour;

VHDL/fifo_rptr_empty.vhdl
library IEEE;
use IEEE.std_logic_1164.all;
use IEEE.numeric_std.all;

entity fifo_rptr_empty is generic(addressSize:integer:=8);
    port(
        rempty: out std_logic;                                  --Active HIGH when readpointer is equal to writepointer (see paper)
        raddr: out std_logic_vector(addressSize-1 downto 0);
        rptr: out std_logic_vector(addressSize downto 0);
        rq2_wptr: in std_logic_vector(addressSize downto 0);
        rinc: in std_logic;
        rclk: in std_logic;
        rrst_n: in std_logic
    );
end entity fifo_rptr_empty;

architecture fifo_rptr_empty_behaviour of fifo_rptr_empty is
    signal rbin: std_logic_vector(addressSize downto 0);
    signal rgraynext: std_logic_vector(addressSize downto 0);
    signal rbinnext: std_logic_vector(addressSize downto 0);
    signal rempty_val: std_logic;
    signal rempty_tmp: std_logic;

    function To_Std_Logic(L: BOOLEAN) return std_ulogic is
    begin
        if L then
          return('1');
       else
          return('0');
       end if;
    end function To_Std_Logic; 

    function Std_Logic_To_Std_Logic_Vector(b: std_logic) return std_logic_vector is
    variable ret: std_logic_vector(addressSize downto 0);
    begin
        ret := (others => '0');
        ret(0) := b;
        return ret;
    end function Std_Logic_To_Std_Logic_Vector; 

    begin
        raddr <= rbin(addressSize-1 downto 0);
        rbinnext <= std_logic_vector(unsigned(rbin)+unsigned(Std_Logic_To_Std_Logic_Vector(rinc and (not rempty_tmp))) );
        rgraynext <= std_logic_vector(shift_right(unsigned(rbinnext),1)) xor rbinnext;
        rempty_val <= To_Std_logic(rgraynext = rq2_wptr);

        process(rclk,rrst_n)
        begin
            if rising_edge(rclk) or falling_edge(rrst_n) then
                if (rrst_n='0') then
                    --Pointer
                    rbin <= (others => '0');
                    rptr <= (others => '0');
                    --FIFO empty
                    rempty <= '1';
                    rempty_tmp <= '1';
                else
                    --Pointer
                    rbin <= rbinnext;
                    rptr <= rgraynext;
                    --FIFO empty
                    rempty <= rempty_val;
                    rempty_tmp <= rempty_val;
                end if;
            end if;
        end process;

    end architecture fifo_rptr_empty_behaviour;

VHDL/fifo_mem.vhdl
library IEEE;
use IEEE.std_logic_1164.all;
use IEEE.numeric_std.all;


entity fifo_mem is generic(dataSize:integer:=8;addressSize:integer:=8);
    port(
        rdata: out std_logic_vector(dataSize-1 downto 0);
        wdata: in std_logic_vector(dataSize-1 downto 0);
        raddr: in std_logic_vector(addressSize-1 downto 0);
        waddr: in std_logic_vector(addressSize-1 downto 0);
        wclken: in std_logic;
        wfull: in std_logic;
        wclk: in std_logic
    );
end entity fifo_mem;
architecture fifo_mem_behaviour of fifo_mem is
    subtype WORD is std_logic_vector(dataSize-1 downto 0);
    type MEMORY is array(0 to 2**addressSize-1) of WORD;
    signal ram:MEMORY;
    
    begin
        process(wclk,wdata,raddr)
        variable ram_waddr:natural range 0 to 2**addressSize-1;
        variable ram_raddr:natural range 0 to 2**addressSize-1;
        begin
            ram_waddr := to_integer(UNSIGNED(waddr));
            ram_raddr := to_integer(UNSIGNED(raddr));
            rdata <= ram(ram_raddr);

            if rising_edge(wclk) then
                if (wclken='1' and wfull='0') then
                    ram(ram_waddr) <= wdata;
                end if;

            end if;
        end process;
    end architecture fifo_mem_behaviour;

VHDL/fifo_sync_w2r.vhdl
library IEEE;
use IEEE.std_logic_1164.all;
use IEEE.numeric_std.all;

entity fifo_sync_w2r is generic(addressSize:integer:=8);
    port(
        rq2_wptr: out std_logic_vector(addressSize downto 0);
        wptr: in std_logic_vector(addressSize downto 0);
        rrst_n: in std_logic;
        rclk: in std_logic
    );
end entity fifo_sync_w2r;

architecture fifo_sync_w2r_behaviour of fifo_sync_w2r is
    signal rq1_wptr: std_logic_vector(addressSize downto 0);
    
    begin
        process(rclk,rrst_n)
        begin
            if rising_edge(rclk) or falling_edge(rrst_n) then
                if (rrst_n='0') then
                    rq2_wptr <= (others => '0');
                    rq1_wptr <= (others => '0');
                else
                    rq2_wptr <= rq1_wptr;
                    rq1_wptr <= wptr;
                end if;
            end if;
        end process;
    end architecture fifo_sync_w2r_behaviour;

VHDL/fifo_sync_r2w.vhdl
library IEEE;
use IEEE.std_logic_1164.all;
use IEEE.numeric_std.all;

entity fifo_sync_r2w is generic(addressSize:integer:=8);
    port(
        wq2_rptr: out std_logic_vector(addressSize downto 0);
        rptr: in std_logic_vector(addressSize downto 0);
        wrst_n: in std_logic;
        wclk: in std_logic
    );
end entity fifo_sync_r2w;

architecture fifo_sync_r2w_behaviour of fifo_sync_r2w is
    signal wq1_rptr: std_logic_vector(addressSize downto 0);
    
    begin
        process(wclk,wrst_n)
        begin
            if rising_edge(wclk) or falling_edge(wrst_n) then
                if (wrst_n='0') then
                    wq2_rptr <= (others => '0');
                    wq1_rptr <= (others => '0');
                else
                    wq2_rptr <= wq1_rptr;
                    wq1_rptr <= rptr;
                end if;
            end if;
        end process;
    end architecture fifo_sync_r2w_behaviour;

VHDL/fifo.vhdl
library IEEE;
use IEEE.std_logic_1164.all;
use IEEE.numeric_std.all;


entity fifo is generic(dataSize:integer:=8;addressSize:integer:=8);
    port(
        rdata: out std_logic_vector(dataSize-1 downto 0);
        wfull: out std_logic;
        rempty: out std_logic;
        wdata: in std_logic_vector(dataSize-1 downto 0);
        winc, wclk, wrst_n: in std_logic;
        rinc, rclk, rrst_n: in std_logic
    );
end entity fifo;
architecture fifo_behaviour of fifo is
    component fifo_sync_r2w 
    generic(addressSize:integer:=8);
    port(
        wq2_rptr: out std_logic_vector(addressSize downto 0);
        rptr: in std_logic_vector(addressSize downto 0);
        wrst_n: in std_logic;
        wclk: in std_logic        
    );
    end component fifo_sync_r2w;

    component fifo_sync_w2r
    generic(addressSize:integer:=8);
    port(
        rq2_wptr: out std_logic_vector(addressSize downto 0);
        wptr: in std_logic_vector(addressSize downto 0);
        rrst_n: in std_logic;
        rclk: in std_logic   
    );
    end component fifo_sync_w2r;

    component fifo_mem 
    generic(dataSize:integer:=8;addressSize:integer:=8);
    port(
        rdata: out std_logic_vector(dataSize-1 downto 0);
        wdata: in std_logic_vector(dataSize-1 downto 0);
        raddr: in std_logic_vector(addressSize-1 downto 0);
        waddr: in std_logic_vector(addressSize-1 downto 0);
        wclken: in std_logic;
        wfull: in std_logic;
        wclk: in std_logic
    );
    end component fifo_mem;

    component fifo_rptr_empty 
    generic(addressSize:integer:=8);
    port(
        rempty: out std_logic;
        raddr: out std_logic_vector(addressSize-1 downto 0);
        rptr: out std_logic_vector(addressSize downto 0);
        rq2_wptr: in std_logic_vector(addressSize downto 0);
        rinc: in std_logic;
        rclk: in std_logic;
        rrst_n: in std_logic
    );
    end component fifo_rptr_empty;

    component fifo_wptr_full 
    generic(addressSize:integer:=8);
    port(
        wfull: out std_logic;
        waddr: out std_logic_vector(addressSize-1 downto 0);
        wptr: out std_logic_vector(addressSize downto 0);
        wq2_rptr: in std_logic_vector(addressSize downto 0);
        winc: in std_logic;
        wclk: in std_logic;
        wrst_n: in std_logic
    );
    end component fifo_wptr_full;

    signal waddr, raddr: std_logic_vector(addressSize-1 downto 0);
    signal wptr, rptr, wq2_rptr, rq2_wptr: std_logic_vector(addressSize downto 0);
    signal wfull_var: std_logic;
begin
    wfull <= wfull_var;
    sync_r2w: fifo_sync_r2w generic map(addressSize => addressSize) port map(wq2_rptr, rptr, wrst_n, wclk);
    sync_w2r: fifo_sync_w2r generic map(addressSize => addressSize) port map(rq2_wptr, wptr, rrst_n, rclk);
    mem: fifo_mem generic map(dataSize =>dataSize, addressSize => addressSize) port map(rdata, wdata, raddr, waddr, winc, wfull_var, wclk);
    rptr_empty: fifo_rptr_empty generic map(addressSize => addressSize) port map(rempty, raddr, rptr, rq2_wptr, rinc, rclk, rrst_n);
    wptr_full: fifo_wptr_full generic map(addressSize => addressSize) port map(wfull_var, waddr, wptr, wq2_rptr, winc, wclk, wrst_n);
    
end architecture fifo_behaviour;

VHDL/sa_reader.vhdl
library work;
use work.array_vector_package.all;

library ieee;
use ieee.std_logic_1164.all;
use ieee.numeric_std.all;

entity sa_reader is
	generic (
		systolicArraySize:integer := 8;	-- for setting the size of the calculation matrix
		bitSize:integer := 8;			-- fixed to 8 for this project
		counterSize : integer := 8		-- how large is the matrix that was calculated
	);    
	port (
		readMatrixToFifo : in std_logic;															-- control signal if this devics should work (='1')
		readMatrix : in std_2d_vector_array(0 to systolicArraySize-1, 0 to systolicArraySize-1);	-- 2D data input (of: std_logic_vector(bitSize-1 downto 0) )
		wFullFIFO : in std_logic;
		wDataToFIFO : out std_logic_vector(bitSize-1 downto 0);
		wClkFIFO, wIncFIFO, wRstFIFO : out std_logic;
		finished : out std_logic	-- reqired: "readMatrixToFifo <= '1'; wait until finished = '1'; readMatrixToFifo <= '0';"
	);
end sa_reader;

architecture behavior of sa_reader is
	
begin
	process begin
		if readMatrixToFifo /= '1' then
			assert false report "Waiting for: readMatrixToFIFO";
			wait until readMatrixToFifo = '1';
		end if;
		
		-- initialize FIFO
		wIncFIFO <= '1';
		wait for 1 ns;
		wClkFIFO <= '0';
		wait for 1 ns;
		wRstFIFO <= '0';	-- resets on 0
		wait for 1 ns;
		wClkFIFO <= '1';	-- reset here
		wait for 1 ns;
		wRstFIFO <= '1';	-- do not reset anymore
		wait for 1 ns;
		wIncFIFO <= '1';	-- increment pointer when writing
		wait for 1 ns;
		
		-- loop through 2D Data (of: std_logic_vector(bitSize-1 downto 0) ) (in row (then column) order)
		for j in 0 to counterSize-1 loop
			for i in 0 to counterSize-1 loop
				wClkFIFO <= '0';
				wait for 1 ns;
				
				if wFullFIFO /= '0' then	-- wait for FIFO to be writeable
					assert false report "Waiting for: wFullFIFO";
					wait until wFullFIFO = '0';
				end if;
				
				wDataToFIFO <= readMatrix(i, j);	-- serialize data to FIFO
				wait for 1 ns;
				
				wClkFIFO <= '1';	-- rising clock edge for FIFO -> write data
				wait for 1 ns;
			end loop;
		end loop;
		
		finished <= '1';	-- it is required to: "readMatrixToFifo <= '1'; wait until finished = '1'; readMatrixToFifo <= '0';"
		wait for 1 ns;
		finished <= '0';
	end process;
end behavior;

VHDL/sa_reader_tb.vhdl
library work;
use work.array_vector_package.all;

library ieee;
use ieee.std_logic_1164.all;
use ieee.numeric_std.all;

entity sa_reader_tb is
end sa_reader_tb;

architecture behavior of sa_reader_tb is
	component sa_reader is
		generic (
			systolicArraySize:integer := 8;	-- for setting the size of the calculation matrix
			bitSize:integer := 8;			-- fixed to 8 for this project
			counterSize : integer := 8		-- how large is the matrix that was calculated
		);    
		port (
			readMatrixToFifo : in std_logic;															-- control signal if this devics should work (='1')
			readMatrix : in std_2d_vector_array(0 to systolicArraySize-1, 0 to systolicArraySize-1);	-- 2D data input (of: std_logic_vector(bitSize-1 downto 0) )
			wFullFIFO : in std_logic;
			wDataToFIFO : out std_logic_vector(bitSize-1 downto 0);
			wClkFIFO, wIncFIFO, wRstFIFO : out std_logic;
			finished : out std_logic	-- reqired: "readMatrixToFifo <= '1'; wait until finished = '1'; readMatrixToFifo <= '0';"
		);
	end component sa_reader;
	
	component fifo is -- first-in first-out (parallel-in parallel-out)
		generic(dataSize:integer:=8;addressSize:integer:=8);
        port(
            rdata: out std_logic_vector(dataSize-1 downto 0);
            wfull: out std_logic;
            rempty: out std_logic;
            wdata: in std_logic_vector(dataSize-1 downto 0);
            winc, wclk, wrst_n: in std_logic;
            rinc, rclk, rrst_n: in std_logic
    );
	end component fifo;
	
	constant systolicArraySize : integer := 8;
	constant bitSize : integer := 8;
	constant counterSize : integer := 8;
	
	signal readMatrixToFifo : std_logic;															-- control signal if this devics should work (='1')
	signal readMatrix : std_2d_vector_array(0 to systolicArraySize-1, 0 to systolicArraySize-1);	-- 2D data input (of: std_logic_vector(bitSize-1 downto 0) )
	signal wFullFIFO : std_logic;
	signal wDataToFIFO : std_logic_vector(bitSize-1 downto 0);
	signal wClkFIFO, wIncFIFO, wRstFIFO, rIncFIFO, rClkFIFO, rRstFIFO: std_logic;
	signal finished : std_logic;
	
	signal bufferFillMatrix : std_logic_vector(bitSize-1 downto 0);
	
	signal readFromFIFO : std_logic_vector(bitSize-1 downto 0);
	signal readFIFOempty: std_logic;
	
	signal c : integer := 1;
	
begin
	sa_reader1 : sa_reader generic map(systolicArraySize, 8, 8) port map(readMatrixToFifo, readMatrix, wFullFIFO, wDataToFIFO, wClkFIFO, wIncFIFO, wRstFIFO, finished);
	fifo1 : fifo generic map(bitSize, counterSize) port map(readFromFIFO, wFullFIFO, readFIFOempty, wDataToFIFO, wIncFIFO, wClkFIFO, wRstFIFO, rIncFIFO, rClkFIFO, rRstFIFO);
	
	process begin
		-- fill 2D Data
		for j in 0 to systolicArraySize-1 loop
			for i in 0 to systolicArraySize-1 loop
				bufferFillMatrix <= std_logic_vector(to_unsigned(c, bitSize));
				wait for 1 ns;
				readMatrix(i, j) <= bufferFillMatrix;	-- to the correct filling in gtkwave
				wait for 1 ns;
				c <= c+1;
				wait for 1 ns;
			end loop;
		end loop;
		
		
		
		-- write 2D Data to fifo
		readMatrixToFifo <= '1';
		wait until finished = '1';
		readMatrixToFifo <= '0';
		
		wait for 50 ns;
		
		
		
		--initialize
		rIncFIFO <= '0';
		wait for 1 ns;
		rRstFIFO <= '0';	-- reset on next clk
		wait for 1 ns;
		rClkFIFO <= '0';
		wait for 1 ns;
		rClkFIFO <= '1';
		wait for 1 ns;
		rRstFIFO <= '1';	-- do not reset anymore
		wait for 1 ns;
		rIncFIFO <= '1';	-- increment read pointer by clock
		wait for 1 ns;
		
		--read out FIFO
		for i in 0 to systolicArraySize*systolicArraySize + 1 loop
			rClkFIFO <= '0';
			wait for 1 ns;
			-- read out of fifo is parallel; watch: "readFromFIFO" for data
			rClkFIFO <= '1';
			wait for 1 ns;
		end loop;
		
		wait for 50 ns;
		
		wait;
	end process;
end behavior;

VHDL/sa_reader_tb.vcd
$date
  Wed Mar 23 17:45:45 2022
$end
$version
  GHDL v0
$end
$timescale
  1 fs
$end
$scope module standard $end
$upscope $end
$scope module std_logic_1164 $end
$upscope $end
$scope module numeric_std $end
$upscope $end
$scope module array_vector_package $end
$upscope $end
$scope module sa_reader_tb $end
$var reg 1 ! readmatrixtofifo $end
$comment readmatrix is not handled $end
$var reg 1 " wfullfifo $end
$var reg 8 # wdatatofifo[7:0] $end
$var reg 1 $ wclkfifo $end
$var reg 1 % wincfifo $end
$var reg 1 & wrstfifo $end
$var reg 1 ' rincfifo $end
$var reg 1 ( rclkfifo $end
$var reg 1 ) rrstfifo $end
$var reg 1 * finished $end
$var reg 8 + bufferfillmatrix[7:0] $end
$var reg 8 , readfromfifo[7:0] $end
$var reg 1 - readfifoempty $end
$var integer 32 . c $end
$scope module sa_reader1 $end
$var reg 1 / readmatrixtofifo $end
$comment readmatrix is not handled $end
$var reg 1 0 wfullfifo $end
$var reg 8 1 wdatatofifo[7:0] $end
$var reg 1 2 wclkfifo $end
$var reg 1 3 wincfifo $end
$var reg 1 4 wrstfifo $end
$var reg 1 5 finished $end
$upscope $end
$scope module fifo1 $end
$var reg 8 6 rdata[7:0] $end
$var reg 1 7 wfull $end
$var reg 1 8 rempty $end
$var reg 8 9 wdata[7:0] $end
$var reg 1 : winc $end
$var reg 1 ; wclk $end
$var reg 1 < wrst_n $end
$var reg 1 = rinc $end
$var reg 1 > rclk $end
$var reg 1 ? rrst_n $end
$var reg 8 @ waddr[7:0] $end
$var reg 8 A raddr[7:0] $end
$var reg 9 B wptr[8:0] $end
$var reg 9 C rptr[8:0] $end
$var reg 9 D wq2_rptr[8:0] $end
$var reg 9 E rq2_wptr[8:0] $end
$var reg 1 F wfull_var $end
$scope module sync_r2w $end
$var reg 9 G wq2_rptr[8:0] $end
$var reg 9 H rptr[8:0] $end
$var reg 1 I wrst_n $end
$var reg 1 J wclk $end
$var reg 9 K wq1_rptr[8:0] $end
$upscope $end
$scope module sync_w2r $end
$var reg 9 L rq2_wptr[8:0] $end
$var reg 9 M wptr[8:0] $end
$var reg 1 N rrst_n $end
$var reg 1 O rclk $end
$var reg 9 P rq1_wptr[8:0] $end
$upscope $end
$scope module mem $end
$var reg 8 Q rdata[7:0] $end
$var reg 8 R wdata[7:0] $end
$var reg 8 S raddr[7:0] $end
$var reg 8 T waddr[7:0] $end
$var reg 1 U wclken $end
$var reg 1 V wfull $end
$var reg 1 W wclk $end
$comment ram is not handled $end
$upscope $end
$scope module rptr_empty $end
$var reg 1 X rempty $end
$var reg 8 Y raddr[7:0] $end
$var reg 9 Z rptr[8:0] $end
$var reg 9 [ rq2_wptr[8:0] $end
$var reg 1 \ rinc $end
$var reg 1 ] rclk $end
$var reg 1 ^ rrst_n $end
$var reg 9 _ rbin[8:0] $end
$var reg 9 ` rgraynext[8:0] $end
$var reg 9 a rbinnext[8:0] $end
$var reg 1 b rempty_val $end
$var reg 1 c rempty_tmp $end
$upscope $end
$scope module wptr_full $end
$var reg 1 d wfull $end
$var reg 8 e waddr[7:0] $end
$var reg 9 f wptr[8:0] $end
$var reg 9 g wq2_rptr[8:0] $end
$var reg 1 h winc $end
$var reg 1 i wclk $end
$var reg 1 j wrst_n $end
$var reg 9 k wbin[8:0] $end
$var reg 9 l wgraynext[8:0] $end
$var reg 9 m wbinnext[8:0] $end
$var reg 1 n wfull_val $end
$var reg 1 o wfull_tmp $end
$upscope $end
$upscope $end
$upscope $end
$enddefinitions $end
#0
U!
U"
bUUUUUUUU #
U$
U%
U&
U'
U(
U)
U*
b00000001 +
bUUUUUUUU ,
U-
b1 .
U/
U0
bUUUUUUUU 1
U2
U3
U4
U5
bUUUUUUUU 6
U7
U8
bUUUUUUUU 9
U:
U;
U<
U=
U>
U?
bUUUUUUUU @
bUUUUUUUU A
bUUUUUUUUU B
bUUUUUUUUU C
bUUUUUUUUU D
bUUUUUUUUU E
UF
bUUUUUUUUU G
bUUUUUUUUU H
UI
UJ
bUUUUUUUUU K
bUUUUUUUUU L
bUUUUUUUUU M
UN
UO
bUUUUUUUUU P
bUUUUUUUU Q
bUUUUUUUU R
bUUUUUUUU S
bUUUUUUUU T
UU
UV
UW
UX
bUUUUUUUU Y
bUUUUUUUUU Z
bUUUUUUUUU [
U\
U]
U^
bUUUUUUUUU _
bXXXXXXXXX `
bXXXXXXXXX a
0b
Uc
Ud
bUUUUUUUU e
bUUUUUUUUU f
bUUUUUUUUU g
Uh
Ui
Uj
bUUUUUUUUU k
bXXXXXXXXX l
bXXXXXXXXX m
0n
Uo
#1000000
#2000000
b10 .
#3000000
b00000010 +
#4000000
#5000000
b11 .
#6000000
b00000011 +
#7000000
#8000000
b100 .
#9000000
b00000100 +
#10000000
#11000000
b101 .
#12000000
b00000101 +
#13000000
#14000000
b110 .
#15000000
b00000110 +
#16000000
#17000000
b111 .
#18000000
b00000111 +
#19000000
#20000000
b1000 .
#21000000
b00001000 +
#22000000
#23000000
b1001 .
#24000000
b00001001 +
#25000000
#26000000
b1010 .
#27000000
b00001010 +
#28000000
#29000000
b1011 .
#30000000
b00001011 +
#31000000
#32000000
b1100 .
#33000000
b00001100 +
#34000000
#35000000
b1101 .
#36000000
b00001101 +
#37000000
#38000000
b1110 .
#39000000
b00001110 +
#40000000
#41000000
b1111 .
#42000000
b00001111 +
#43000000
#44000000
b10000 .
#45000000
b00010000 +
#46000000
#47000000
b10001 .
#48000000
b00010001 +
#49000000
#50000000
b10010 .
#51000000
b00010010 +
#52000000
#53000000
b10011 .
#54000000
b00010011 +
#55000000
#56000000
b10100 .
#57000000
b00010100 +
#58000000
#59000000
b10101 .
#60000000
b00010101 +
#61000000
#62000000
b10110 .
#63000000
b00010110 +
#64000000
#65000000
b10111 .
#66000000
b00010111 +
#67000000
#68000000
b11000 .
#69000000
b00011000 +
#70000000
#71000000
b11001 .
#72000000
b00011001 +
#73000000
#74000000
b11010 .
#75000000
b00011010 +
#76000000
#77000000
b11011 .
#78000000
b00011011 +
#79000000
#80000000
b11100 .
#81000000
b00011100 +
#82000000
#83000000
b11101 .
#84000000
b00011101 +
#85000000
#86000000
b11110 .
#87000000
b00011110 +
#88000000
#89000000
b11111 .
#90000000
b00011111 +
#91000000
#92000000
b100000 .
#93000000
b00100000 +
#94000000
#95000000
b100001 .
#96000000
b00100001 +
#97000000
#98000000
b100010 .
#99000000
b00100010 +
#100000000
#101000000
b100011 .
#102000000
b00100011 +
#103000000
#104000000
b100100 .
#105000000
b00100100 +
#106000000
#107000000
b100101 .
#108000000
b00100101 +
#109000000
#110000000
b100110 .
#111000000
b00100110 +
#112000000
#113000000
b100111 .
#114000000
b00100111 +
#115000000
#116000000
b101000 .
#117000000
b00101000 +
#118000000
#119000000
b101001 .
#120000000
b00101001 +
#121000000
#122000000
b101010 .
#123000000
b00101010 +
#124000000
#125000000
b101011 .
#126000000
b00101011 +
#127000000
#128000000
b101100 .
#129000000
b00101100 +
#130000000
#131000000
b101101 .
#132000000
b00101101 +
#133000000
#134000000
b101110 .
#135000000
b00101110 +
#136000000
#137000000
b101111 .
#138000000
b00101111 +
#139000000
#140000000
b110000 .
#141000000
b00110000 +
#142000000
#143000000
b110001 .
#144000000
b00110001 +
#145000000
#146000000
b110010 .
#147000000
b00110010 +
#148000000
#149000000
b110011 .
#150000000
b00110011 +
#151000000
#152000000
b110100 .
#153000000
b00110100 +
#154000000
#155000000
b110101 .
#156000000
b00110101 +
#157000000
#158000000
b110110 .
#159000000
b00110110 +
#160000000
#161000000
b110111 .
#162000000
b00110111 +
#163000000
#164000000
b111000 .
#165000000
b00111000 +
#166000000
#167000000
b111001 .
#168000000
b00111001 +
#169000000
#170000000
b111010 .
#171000000
b00111010 +
#172000000
#173000000
b111011 .
#174000000
b00111011 +
#175000000
#176000000
b111100 .
#177000000
b00111100 +
#178000000
#179000000
b111101 .
#180000000
b00111101 +
#181000000
#182000000
b111110 .
#183000000
b00111110 +
#184000000
#185000000
b111111 .
#186000000
b00111111 +
#187000000
#188000000
b1000000 .
#189000000
b01000000 +
#190000000
#191000000
b1000001 .
#192000000
1!
1%
1/
13
1:
1U
1h
#193000000
0$
02
0;
0J
0W
0i
#194000000
0&
04
0<
0I
0j
#195000000
0"
1$
00
12
07
1;
b00000000 @
b000000000 B
b000000000 D
0F
b000000000 G
1J
b000000000 K
b000000000 M
b00000000 T
0V
1W
0d
b00000000 e
b000000000 f
b000000000 g
1i
b000000000 k
b000000001 l
b000000001 m
0o
#196000000
1&
14
1<
1I
1j
#197000000
#198000000
0$
02
0;
0J
0W
0i
#199000000
b00000001 #
b00000001 1
b00000001 9
b00000001 R
#200000000
1$
12
1;
b00000001 @
b000000001 B
1J
bUUUUUUUUU K
b000000001 M
b00000001 T
1W
b00000001 e
b000000001 f
1i
b000000001 k
b000000011 l
b000000010 m
#201000000
0$
b00000001 ,
02
b00000001 6
0;
0J
b00000001 Q
0W
0i
#202000000
b00000010 #
b00000010 1
b00000010 9
b00000010 R
#203000000
1$
12
1;
b00000010 @
b000000011 B
bUUUUUUUUU D
bUUUUUUUUU G
1J
b000000011 M
b00000010 T
1W
b00000010 e
b000000011 f
bUUUUUUUUU g
1i
b000000010 k
b000000010 l
b000000011 m
#204000000
0$
02
0;
0J
0W
0i
#205000000
b00000011 #
b00000011 1
b00000011 9
b00000011 R
#206000000
1$
12
1;
b00000011 @
b000000010 B
1J
b000000010 M
b00000011 T
1W
b00000011 e
b000000010 f
1i
b000000011 k
b000000110 l
b000000100 m
#207000000
0$
02
0;
0J
0W
0i
#208000000
b00000100 #
b00000100 1
b00000100 9
b00000100 R
#209000000
1$
12
1;
b00000100 @
b000000110 B
1J
b000000110 M
b00000100 T
1W
b00000100 e
b000000110 f
1i
b000000100 k
b000000111 l
b000000101 m
#210000000
0$
02
0;
0J
0W
0i
#211000000
b00000101 #
b00000101 1
b00000101 9
b00000101 R
#212000000
1$
12
1;
b00000101 @
b000000111 B
1J
b000000111 M
b00000101 T
1W
b00000101 e
b000000111 f
1i
b000000101 k
b000000101 l
b000000110 m
#213000000
0$
02
0;
0J
0W
0i
#214000000
b00000110 #
b00000110 1
b00000110 9
b00000110 R
#215000000
1$
12
1;
b00000110 @
b000000101 B
1J
b000000101 M
b00000110 T
1W
b00000110 e
b000000101 f
1i
b000000110 k
b000000100 l
b000000111 m
#216000000
0$
02
0;
0J
0W
0i
#217000000
b00000111 #
b00000111 1
b00000111 9
b00000111 R
#218000000
1$
12
1;
b00000111 @
b000000100 B
1J
b000000100 M
b00000111 T
1W
b00000111 e
b000000100 f
1i
b000000111 k
b000001100 l
b000001000 m
#219000000
0$
02
0;
0J
0W
0i
#220000000
b00001000 #
b00001000 1
b00001000 9
b00001000 R
#221000000
1$
12
1;
b00001000 @
b000001100 B
1J
b000001100 M
b00001000 T
1W
b00001000 e
b000001100 f
1i
b000001000 k
b000001101 l
b000001001 m
#222000000
0$
02
0;
0J
0W
0i
#223000000
b00001001 #
b00001001 1
b00001001 9
b00001001 R
#224000000
1$
12
1;
b00001001 @
b000001101 B
1J
b000001101 M
b00001001 T
1W
b00001001 e
b000001101 f
1i
b000001001 k
b000001111 l
b000001010 m
#225000000
0$
02
0;
0J
0W
0i
#226000000
b00001010 #
b00001010 1
b00001010 9
b00001010 R
#227000000
1$
12
1;
b00001010 @
b000001111 B
1J
b000001111 M
b00001010 T
1W
b00001010 e
b000001111 f
1i
b000001010 k
b000001110 l
b000001011 m
#228000000
0$
02
0;
0J
0W
0i
#229000000
b00001011 #
b00001011 1
b00001011 9
b00001011 R
#230000000
1$
12
1;
b00001011 @
b000001110 B
1J
b000001110 M
b00001011 T
1W
b00001011 e
b000001110 f
1i
b000001011 k
b000001010 l
b000001100 m
#231000000
0$
02
0;
0J
0W
0i
#232000000
b00001100 #
b00001100 1
b00001100 9
b00001100 R
#233000000
1$
12
1;
b00001100 @
b000001010 B
1J
b000001010 M
b00001100 T
1W
b00001100 e
b000001010 f
1i
b000001100 k
b000001011 l
b000001101 m
#234000000
0$
02
0;
0J
0W
0i
#235000000
b00001101 #
b00001101 1
b00001101 9
b00001101 R
#236000000
1$
12
1;
b00001101 @
b000001011 B
1J
b000001011 M
b00001101 T
1W
b00001101 e
b000001011 f
1i
b000001101 k
b000001001 l
b000001110 m
#237000000
0$
02
0;
0J
0W
0i
#238000000
b00001110 #
b00001110 1
b00001110 9
b00001110 R
#239000000
1$
12
1;
b00001110 @
b000001001 B
1J
b000001001 M
b00001110 T
1W
b00001110 e
b000001001 f
1i
b000001110 k
b000001000 l
b000001111 m
#240000000
0$
02
0;
0J
0W
0i
#241000000
b00001111 #
b00001111 1
b00001111 9
b00001111 R
#242000000
1$
12
1;
b00001111 @
b000001000 B
1J
b000001000 M
b00001111 T
1W
b00001111 e
b000001000 f
1i
b000001111 k
b000011000 l
b000010000 m
#243000000
0$
02
0;
0J
0W
0i
#244000000
b00010000 #
b00010000 1
b00010000 9
b00010000 R
#245000000
1$
12
1;
b00010000 @
b000011000 B
1J
b000011000 M
b00010000 T
1W
b00010000 e
b000011000 f
1i
b000010000 k
b000011001 l
b000010001 m
#246000000
0$
02
0;
0J
0W
0i
#247000000
b00010001 #
b00010001 1
b00010001 9
b00010001 R
#248000000
1$
12
1;
b00010001 @
b000011001 B
1J
b000011001 M
b00010001 T
1W
b00010001 e
b000011001 f
1i
b000010001 k
b000011011 l
b000010010 m
#249000000
0$
02
0;
0J
0W
0i
#250000000
b00010010 #
b00010010 1
b00010010 9
b00010010 R
#251000000
1$
12
1;
b00010010 @
b000011011 B
1J
b000011011 M
b00010010 T
1W
b00010010 e
b000011011 f
1i
b000010010 k
b000011010 l
b000010011 m
#252000000
0$
02
0;
0J
0W
0i
#253000000
b00010011 #
b00010011 1
b00010011 9
b00010011 R
