VHDL/stack.vhdl
library ieee;
use ieee.std_logic_1164.all;
use ieee.numeric_std.all;

entity stack is
    generic(
        bitSize : integer := 8;
        stackSize : integer := 4
    );
    port(
        d  : in  std_logic_vector(bitSize - 1 downto 0); 
        q  : out std_logic_vector(bitSize - 1 downto 0);
        bar_push_pop : in  std_logic; 
        full  : out std_logic; 
        empty : out std_logic; 
        clk     : in  std_logic;
        rst     : in  std_logic
    );
end entity stack;

architecture arch of stack is
    

    	type memory_type is array (0 to stackSize - 1) of std_logic_vector(bitSize - 1 downto 0);
   	signal memory : memory_type;
begin
    main : process(clk, rst) is
        variable stack_pointer : integer range 0 to stackSize := stackSize;
    begin
        if rst = '1' then
		memory <= (others => (others => '0'));
            	empty <= '1';
            	full  <= '0';
            	stack_pointer := stackSize;
        elsif rising_edge(clk) then
            	if bar_push_pop = '1' then --pop
                	if stack_pointer < stackSize then
                    		q <= memory(stack_pointer);
                    		stack_pointer := stack_pointer + 1;
			else
				q <= (others => '0');
                	end if;
            	else  --push
                	if stack_pointer > 0 then
                    		stack_pointer := stack_pointer - 1;
                    		memory(stack_pointer) <= d;
				q <= d;
                	end if;
            	end if;


            	if stack_pointer = stackSize then
               		empty <= '1';
			q <= (others => '0');
            	else
                	empty <= '0';
            	end if;
            	if stack_pointer = 0 then
                	full <= '1';
            	else
                	full <= '0';
            	end if;
        end if;
    end process main;

end architecture arch;

VHDL/stack_tb.vhdl
library work;
use work.array_vector_package.all;

library ieee;
use ieee.std_logic_1164.all;

entity stack_tb is
end stack_tb;

architecture test of stack_tb is
	component stack is
        generic(
        	bitSize : integer := 8;
        	stackSize : integer := 4
   	);
    	port(
       		d  : in  std_logic_vector(bitSize - 1 downto 0); 
        	q  : out std_logic_vector(bitSize - 1 downto 0);
        	bar_push_pop : in  std_logic; 
        	full  : out std_logic; 
        	empty : out std_logic; 
        	clk     : in  std_logic;
        	rst     : in  std_logic
    	);
    	end component stack;
    
	signal d,q: std_logic_vector(7 downto 0)  ;
	signal bar_push_pop, rst, clk, empty, full: std_logic;
	
begin
    stack1: stack generic map(stackSize=>4, bitSize=>8)port map(d => d, q => q, bar_push_pop => bar_push_pop, full => full, empty => empty, clk => clk, rst => rst);
    
	process begin
		clk <= '0';
		bar_push_pop <= '0';
		rst <= '1';
		d <= "00001111";
		wait for 10 ns;
		rst <= '0';
		wait for 10 ns;
		bar_push_pop <= '0';
		
		wait for 10 ns;
		clk <= '1';wait for 10 ns;clk <= '0';wait for 10 ns;
		d <= "10101010";
		clk <= '1';wait for 10 ns;clk <= '0';wait for 10 ns;
		d <= "01010101";
		clk <= '1';wait for 10 ns;clk <= '0';wait for 10 ns;
		--d <= "11110000";
		--clk <= '1';wait for 10 ns;clk <= '0';wait for 10 ns;
		bar_push_pop <= '1';
		clk <= '1';wait for 10 ns;clk <= '0';wait for 10 ns;
		clk <= '1';wait for 10 ns;clk <= '0';wait for 10 ns;
		clk <= '1';wait for 10 ns;clk <= '0';wait for 10 ns;
		clk <= '1';wait for 10 ns;clk <= '0';wait for 10 ns;
		clk <= '1';wait for 10 ns;clk <= '0';wait for 10 ns;
	end process;
end test;

VHDL/stack_tb.vcd
$date
  Mon Mar 21 13:10:33 2022
$end
$version
  GHDL v0
$end
$timescale
  1 fs
$end
$scope module standard $end
$upscope $end
$scope module std_logic_1164 $end
$upscope $end
$scope module numeric_std $end
$upscope $end
$scope module array_vector_package $end
$upscope $end
$scope module stack_tb $end
$var reg 8 ! d[7:0] $end
$var reg 8 " q[7:0] $end
$var reg 1 # bar_push_pop $end
$var reg 1 $ rst $end
$var reg 1 % clk $end
$var reg 1 & empty $end
$var reg 1 ' full $end
$scope module stack1 $end
$var reg 8 ( d[7:0] $end
$var reg 8 ) q[7:0] $end
$var reg 1 * bar_push_pop $end
$var reg 1 + full $end
$var reg 1 , empty $end
$var reg 1 - clk $end
$var reg 1 . rst $end
$comment memory is not handled $end
$upscope $end
$upscope $end
$enddefinitions $end
#0
b00001111 !
bUUUUUUUU "
0#
1$
0%
1&
0'
b00001111 (
bUUUUUUUU )
0*
0+
1,
0-
1.
#10000000
0$
0.
#20000000
#30000000
b00001111 "
1%
0&
b00001111 )
0,
1-
#40000000
0%
0-
#50000000
b10101010 !
b10101010 "
1%
b10101010 (
b10101010 )
1-
#60000000
0%
0-
#70000000
b01010101 !
b01010101 "
1%
b01010101 (
b01010101 )
1-
#80000000
0%
0-
#90000000
1#
1%
1*
1-
#100000000
0%
0-
#110000000
b10101010 "
1%
b10101010 )
1-
#120000000
0%
0-
#130000000
b00001111 "
1%
1&
b00001111 )
1,
1-
#140000000
0%
0-
#150000000
b00000000 "
1%
b00000000 )
1-
